README.rst
setup.cfg
setup.py
fb_messenger/__init__.py
fb_messenger/attachments.py
fb_messenger/client.py
fb_messenger/const.py
fb_messenger/exceptions.py
fb_messenger/interfaces.py
fb_messenger/webhook_attachments.py
fb_messenger/webhooks.py
fb_messenger.egg-info/PKG-INFO
fb_messenger.egg-info/SOURCES.txt
fb_messenger.egg-info/dependency_links.txt
fb_messenger.egg-info/top_level.txt
fb_messenger/types/__init__.py
fb_messenger/types/action_types.py
fb_messenger/types/notification_types.py
fb_messenger/types/webhook_attachment_types.py
fb_messenger/types/webhook_types.py