Metadata-Version: 1.1
Name: fb-messenger
Version: 0.3.0
Summary: Python API client for FB Messenger
Home-page: https://github.com/shananin/Fb_messanger
Author: Artem Shananin (Shananin)
Author-email: artem.shananin@gmail.com
License: MIT
Keywords: fb facebook messenger client api chat
Platform: UNKNOWN
Classifier: Environment :: Web Environment
Classifier: Intended Audience :: Developers
Classifier: License :: OSI Approved :: MIT License
Classifier: Operating System :: OS Independent
Classifier: Programming Language :: Python
Classifier: Programming Language :: Python :: 2.7
Classifier: Programming Language :: Python :: 3.3
Classifier: Programming Language :: Python :: 3.4
Classifier: Programming Language :: Python :: 3.5
Classifier: Programming Language :: Python :: Implementation :: CPython
Classifier: Programming Language :: Python :: Implementation :: PyPy
Classifier: Topic :: Internet :: WWW/HTTP :: Dynamic Content
Classifier: Topic :: Software Development :: Libraries :: Python Modules
